{
    "adana": 30247,
    "adiyaman": 4355,
    "afyonkarahisar": 4225,
    "agri": 2434,
    "aksaray": 2277,
    "amasya": 3424,
    "ankara": 155020,
    "antalya": 43276,
    "ardahan": 1304,
    "artvin": 5788,
    "aydin": 11079,
    "balikesir": 13277,
    "bartin": 3137,
    "batman": 5599,
    "bayburt": 732,
    "bilecik": 1810,
    "bingol": 1163,
    "bitlis": 1086,
    "bolu": 2218,
    "burdur": 716,
    "bursa": 43943,
    "canakkale": 6185,
    "cankiri": 1406,
    "corum": 3976,
    "denizli": 13330,
    "diyarbakir": 10633,
    "duzce": 2402,
    "edirne": 4684,
    "elazig": 4854,
    "erzincan": 3022,
    "erzurum": 7120,
    "eskisehir": 12945,
    "gaziantep": 15447,
    "giresun": 3509,
    "gumushane": 536,
    "hakkari": 2832,
    "hatay": 11098,
    "igdir": 744,
    "isparta": 4738,
    "istanbul": 326768,
    "izmir": 97009,
    "kahramanmaras": 7638,
    "karabuk": 2027,
    "karaman": 1025,
    "kars": 2193,
    "kastamonu": 3726,
    "kayseri": 20295,
    "kilis": 307,
    "kirikkale": 1785,
    "kirklareli": 2550,
    "kirsehir": 1695,
    "kocaeli": 24206,
    "konya": 23680,
    "kutahya": 2846,
    "malatya": 10301,
    "manisa": 11750,
    "mardin": 6116,
    "mersin": 22700,
    "mugla": 17320,
    "mus": 2081,
    "nevsehir": 2064,
    "nigde": 3179,
    "ordu": 6001,
    "osmaniye": 5400,
    "rize": 5162,
    "sakarya": 9164,
    "samsun": 19857,
    "sanliurfa": 8608,
    "siirt": 3281,
    "sinop": 1779,
    "sivas": 10929,
    "sirnak": 2584,
    "tekirdag": 11422,
    "tokat": 6863,
    "trabzon": 23801,
    "tunceli": 1176,
    "usak": 2614,
    "van": 8039,
    "yalova": 3080,
    "yozgat": 4530,
    "zonguldak": 4335
}